setup.py
rioh/__init__.py
rioh.egg-info/PKG-INFO
rioh.egg-info/SOURCES.txt
rioh.egg-info/dependency_links.txt
rioh.egg-info/top_level.txt
rioh/flask/__init__.py
rioh/requests/__init__.py
rioh/wsgi/__init__.py